Metadata-Version: 1.1
Name: openlmi-scripts-journald
Version: 0.2.8
Summary: journald
Home-page: https://github.com/openlmi/openlmi-scripts
Author: Tomas Bzatek
Author-email: tbzatek@redhat.com
License: BSD
Download-URL: https://github.com/openlmi/openlmi-scripts/tarball/master
Platform: Any
Classifier: License :: OSI Approved :: BSD License
Classifier: Operating System :: POSIX :: Linux
Classifier: Topic :: System :: Systems Administration
Classifier: Programming Language :: Python
Classifier: Programming Language :: Python :: 2
Classifier: Programming Language :: Python :: 2.7
Classifier: Intended Audience :: Developers
Classifier: Environment :: Console
